lugo4py/__init__.py
lugo4py/mapper/__init__.py
lugo4py/mapper/src/__init__.py
lugo4py/mapper/src/direction.py
lugo4py/mapper/src/mapper.py
lugo4py/mapper/src/orientation.py
lugo4py/protos/__init__.py
lugo4py/protos/broadcast_pb2.py
lugo4py/protos/broadcast_pb2_grpc.py
lugo4py/protos/health_pb2.py
lugo4py/protos/health_pb2_grpc.py
lugo4py/protos/physics_pb2.py
lugo4py/protos/physics_pb2_grpc.py
lugo4py/protos/remote_pb2.py
lugo4py/protos/remote_pb2_grpc.py
lugo4py/protos/server_pb2.py
lugo4py/protos/server_pb2_grpc.py
lugo4py/rl/__init__.py
lugo4py/rl/src/__init__.py
lugo4py/rl/src/gym.py
lugo4py/rl/src/helper_bots.py
lugo4py/rl/src/interfaces.py
lugo4py/rl/src/remote_control.py
lugo4py/rl/src/training_controller.py
lugo4py/src/__init__.py
lugo4py/src/client.py
lugo4py/src/define_state.py
lugo4py/src/game_snapshot_inspector.py
lugo4py/src/geo.py
lugo4py/src/goal.py
lugo4py/src/helpers.py
lugo4py/src/interface.py
lugo4py/src/loader.py
lugo4py/src/lugo.py
lugo4py/src/specs.py
lugo4py/src/starter.py
lugo4py-1.0.2.dist-info/LICENSE.txt
lugo4py-1.0.2.dist-info/METADATA
lugo4py-1.0.2.dist-info/WHEEL
lugo4py-1.0.2.dist-info/top_level.txt
lugo4py-1.0.2.dist-info/RECORD
